uploadtool/__init__.py
uploadtool/upload.py
uploadtool-0.2.1.dist-info/METADATA
uploadtool-0.2.1.dist-info/WHEEL
uploadtool-0.2.1.dist-info/top_level.txt
uploadtool-0.2.1.dist-info/RECORD
