Metadata-Version: 2.1
Name: uploadtool
Version: 0.2.1
Summary: python uploadtool for convenient.<Windows Only>
Author-email: 2229066748@qq.com
Maintainer: Eagle'sBaby
Maintainer-email: 2229066748@qq.com
License: Apache Licence 2.0
Keywords: pypi,upload,twine
Classifier: Programming Language :: Python
Classifier: Programming Language :: Python :: 3
Requires-Python: >=3
Requires-Dist: twine
Requires-Dist: wheel
